mtgdecktech/__init__.py
mtgdecktech/cli.py
mtgdecktech/mtgdecktech.py
mtgdecktech-0.1.0.dist-info/AUTHORS.md
mtgdecktech-0.1.0.dist-info/LICENSE
mtgdecktech-0.1.0.dist-info/METADATA
mtgdecktech-0.1.0.dist-info/WHEEL
mtgdecktech-0.1.0.dist-info/entry_points.txt
mtgdecktech-0.1.0.dist-info/top_level.txt
mtgdecktech-0.1.0.dist-info/RECORD
