Metadata-Version: 2.1
Name: mtgdecktech
Version: 0.1.0
Summary: Program for generating images for Magic: the Gathering deck tech videos
Home-page: https://github.com/cmeister2/mtgdecktech
Author: Max Dymond
Author-email: cmeister2@gmail.com
License: MIT license
Keywords: mtgdecktech
Platform: UNKNOWN
Classifier: Development Status :: 2 - Pre-Alpha
Classifier: Intended Audience :: Developers
Classifier: License :: OSI Approved :: MIT License
Classifier: Natural Language :: English
Classifier: Programming Language :: Python :: 2
Classifier: Programming Language :: Python :: 2.7
Classifier: Programming Language :: Python :: 3
Classifier: Programming Language :: Python :: 3.4
Classifier: Programming Language :: Python :: 3.5
Classifier: Programming Language :: Python :: 3.6
Classifier: Programming Language :: Python :: 3.7
Requires-Dist: Click (>=6.0)
